odoo/addons/stock_picking_start/README.rst
odoo/addons/stock_picking_start/__init__.py
odoo/addons/stock_picking_start/__manifest__.py
odoo/addons/stock_picking_start/hooks.py
odoo/addons/stock_picking_start/i18n/es.po
odoo/addons/stock_picking_start/i18n/fr.po
odoo/addons/stock_picking_start/i18n/it.po
odoo/addons/stock_picking_start/i18n/stock_picking_start.pot
odoo/addons/stock_picking_start/models/__init__.py
odoo/addons/stock_picking_start/models/res_company.py
odoo/addons/stock_picking_start/models/res_config_settings.py
odoo/addons/stock_picking_start/models/stock_picking.py
odoo/addons/stock_picking_start/readme/CONTRIBUTORS.rst
odoo/addons/stock_picking_start/readme/DESCRIPTION.rst
odoo/addons/stock_picking_start/static/description/icon.png
odoo/addons/stock_picking_start/static/description/index.html
odoo/addons/stock_picking_start/tests/__init__.py
odoo/addons/stock_picking_start/tests/test_stock_picking_start.py
odoo/addons/stock_picking_start/views/res_config_settings.xml
odoo/addons/stock_picking_start/views/stock_picking.xml
odoo_addon_stock_picking_start-16.0.1.2.0.dist-info/METADATA
odoo_addon_stock_picking_start-16.0.1.2.0.dist-info/WHEEL
odoo_addon_stock_picking_start-16.0.1.2.0.dist-info/top_level.txt
odoo_addon_stock_picking_start-16.0.1.2.0.dist-info/RECORD
