Metadata-Version: 2.1
Name: odoo-addon-stock_picking_start
Version: 16.0.1.2.0
Summary: Add button to start picking
Home-page: https://github.com/OCA/stock-logistics-workflow
Author: ACSONE SA/NV,Odoo Community Association (OCA)
Author-email: support@odoo-community.org
License: LGPL-3
Classifier: Programming Language :: Python
Classifier: Framework :: Odoo
Classifier: Framework :: Odoo :: 16.0
Classifier: License :: OSI Approved :: GNU Lesser General Public License v3 (LGPLv3)
Requires-Python: >=3.10
Requires-Dist: odoo<16.1dev,>=16.0a
